Metadata-Version: 1.0
Name: gback
Version: 0.52
Summary: Google Calendar Backup utility.
Home-page: http://github.com/Schwarzschild/gback
Author: Marc Schwarzschild
Author-email: ms@TheBrookhavenGroup.com
License: MIT
Keywords: google,calendar
Platform: UNKNOWN
